kptl/__init__.py
kptl/main.py
kptl/commands/__init__.py
kptl/commands/delete.py
kptl/commands/diff.py
kptl/commands/explain.py
kptl/commands/sync.py
kptl/config/__init__.py
kptl/config/constants.py
kptl/config/logger.py
kptl/helpers/__init__.py
kptl/helpers/api_product_documents.py
kptl/helpers/utils.py
kptl/helpers/validator.py
kptl/konnect/__init__.py
kptl/konnect/api.py
kptl/konnect/models/__init__.py
kptl/konnect/models/schema.py
kptl/konnect/services/__init__.py
kptl/konnect/services/api_product.py
kptl/konnect/services/portal_management.py
kptl-0.10.0.dist-info/METADATA
kptl-0.10.0.dist-info/WHEEL
kptl-0.10.0.dist-info/entry_points.txt
kptl-0.10.0.dist-info/top_level.txt
kptl-0.10.0.dist-info/RECORD
