Metadata-Version: 2.1
Name: kptl
Version: 0.10.0
Summary: A rather opinionated CLI for managing API Products in Kong Konnect.
Home-page: https://github.com/pantsel/konnect-portal-ops-cli
Author: Panagis Tselentis
Author-email: tselentispanagis@gmail.com
Classifier: Programming Language :: Python :: 3
Classifier: License :: OSI Approved :: MIT License
Classifier: Operating System :: OS Independent
Requires-Python: >=3.8
Requires-Dist: PyYAML==6.0.2
Requires-Dist: requests==2.32.3
Provides-Extra: dev
Requires-Dist: pytest; extra == "dev"
